data/3disks.json
data/4disks.json
data/5disks.json
data/6disks.json
extremal_packings/__init__.py
extremal_packings/analysis.py
extremal_packings/catalog.py
extremal_packings/cli.py
extremal_packings/configurations.py
extremal_packings/constraints.py
extremal_packings/contact_graphs.py
extremal_packings/hessian.py
extremal_packings/interface.py
extremal_packings/io.py
extremal_packings/json_loader.py
extremal_packings/perimeter.py
extremal_packings/plotting.py
extremal_packings-0.2.1.dist-info/licenses/LICENSE
extremal_packings-0.2.1.dist-info/METADATA
extremal_packings-0.2.1.dist-info/WHEEL
extremal_packings-0.2.1.dist-info/entry_points.txt
extremal_packings-0.2.1.dist-info/top_level.txt
extremal_packings-0.2.1.dist-info/RECORD
