Metadata-Version: 2.4
Name: extremal-packings
Version: 0.2.1
Summary: Análisis geométrico y espectral de configuraciones extremales de discos tangentes
Home-page: https://github.com/Fhv75/disk-packing-analysis
Author: Fabián Henry Vilaxa
Author-email: Fabián Henry Vilaxa <fabian.henry.vilaxa@alumnos.uta.cl>
License: MIT
Project-URL: Homepage, https://github.com/Fhv75/disk-packing-analysis
Project-URL: Documentation, https://github.com/Fhv75/disk-packing-analysis/blob/main/docs/index.md
Project-URL: Repository, https://github.com/Fhv75/disk-packing-analysis
Project-URL: Bug Tracker, https://github.com/Fhv75/disk-packing-analysis/issues
Keywords: geometry,disk packing,rigid configurations,spectral analysis,contact graphs
Classifier: Development Status :: 4 - Beta
Classifier: Intended Audience :: Science/Research
Classifier: License :: OSI Approved :: MIT License
Classifier: Programming Language :: Python :: 3
Classifier: Programming Language :: Python :: 3.8
Classifier: Programming Language :: Python :: 3.9
Classifier: Programming Language :: Python :: 3.10
Classifier: Programming Language :: Python :: 3.11
Classifier: Programming Language :: Python :: 3.12
Classifier: Topic :: Scientific/Engineering :: Mathematics
Classifier: Topic :: Scientific/Engineering :: Physics
Requires-Python: >=3.8
License-File: LICENSE
Requires-Dist: numpy>=1.20.0
Requires-Dist: scipy>=1.7.0
Requires-Dist: matplotlib>=3.3.0
Requires-Dist: networkx>=2.5
Requires-Dist: click>=8.0.0
Provides-Extra: dev
Requires-Dist: pytest>=7.0; extra == "dev"
Requires-Dist: pytest-cov>=3.0; extra == "dev"
Requires-Dist: black>=22.0; extra == "dev"
Requires-Dist: flake8>=4.0; extra == "dev"
Requires-Dist: mypy>=0.950; extra == "dev"
Dynamic: author
Dynamic: home-page
Dynamic: license-file
Dynamic: requires-python
